cinder_auths/__init__.py
cinder_auths/cinder_auths.py
cinder_auths-0.1.1.dist-info/DESCRIPTION.rst
cinder_auths-0.1.1.dist-info/METADATA
cinder_auths-0.1.1.dist-info/RECORD
cinder_auths-0.1.1.dist-info/WHEEL
cinder_auths-0.1.1.dist-info/entry_points.txt
cinder_auths-0.1.1.dist-info/metadata.json
cinder_auths-0.1.1.dist-info/top_level.txt
