Metadata-Version: 2.0
Name: cinder-auths
Version: 0.1.1
Summary: Cinder Authentication Examples
Home-page: https://github.com/akrog/cinder_auths
Author: Gorka Eguileor
Author-email: gorka@eguileor.com
License: Apache Software License 2.0
Keywords: cinder_auths
Platform: UNKNOWN
Classifier: Development Status :: 2 - Pre-Alpha
Classifier: Intended Audience :: Developers
Classifier: License :: OSI Approved :: Apache Software License
Classifier: Natural Language :: English
Classifier: Programming Language :: Python :: 2
Classifier: Programming Language :: Python :: 2.6
Classifier: Programming Language :: Python :: 2.7
Classifier: Programming Language :: Python :: 3
Classifier: Programming Language :: Python :: 3.3
Classifier: Programming Language :: Python :: 3.4
Classifier: Programming Language :: Python :: 3.5
Requires-Dist: cinder
Requires-Dist: pyotp (==2.2.6)
